[{
  "coordinater": {
      "name": "Captain CHEZHIAN R",
      "designation": "NCC Army Coordinator",
      "image_path": "/static/images/ncc/army/chairman.webp",
      "message":" "
  },
  "members": {
    "name": [
      "AKASH G",
      "GOKULAKRISHNAN M",
      "JACOBGIDEONRAJ R",
      "JITVAN S",
      "MUTHU KUMARAN A",
      "NAVEN A",
      "NAVEEN KUMAR T",
      "SURYA DEVU V",
      "THARUN P",
      "VIMALKANTH B",
      "VINEETH N",
      "AARTHI K K",
      "KEERTHANA B",
      "RAKSHAA P",
      "SUBHA SREE M",
      "AKASHBABU K",
      "CHARLES S",
      "CHITHIRAI SELVAN G",
      "ESAKKIRAJAN G",
      "INNDHAR M",
      "KATHIRVELS",
      "LOKESH THAMBIRAN R",
      "NISHANTH V",
      "SADIK ALI K",
      "UTHAYA KUMAR S",
      "ABINAYA V",
      "RUTHRA S",
      "SAI DHARSHINI D",
      "BALAJI S",
      "BHARATH S",
      "GOWTHAM R",
      "HARESH R",
      "JEEVESH G",
      "LAKSHMIPRASAD P",
      "MUTHUKUMAR A",
      "NANDISH K",
      "POZHILAZHAGAN E",
      "PRANAV S",
      "ROHAN B",
      "SATHEESHWARAN G",
      "SERRENKUMAR D",
      "SUGAVANESHWARAN M",
      "CHARUMATHI S",
      "DEEKSHANA K",
      "PREETHA N",
      "PRIYADHARSHINI M",
      "SAHANA P",
      "SHENBAGAM R",
      "SREENIDHI B V",
      "SRILEKHA G"
    ],
    "regiment_no": [
      "TN22SDA614501",
      "TN22SDA614503",
      "TN22SDA614505",
      "TN22SDA614506",
      "TN22SDA614507",
      "TN22SDA614508",
      "TN22SDA614509",
      "TN22SDA614510",
      "TN22SDA614511",
      "TN22SDA614512",
      "TN22SDA614513",
      "TN22SWA614514",
      "TN22SWA614521",
      "TN22SWA614523",
      "TN22SWA614525",
      "TN23SDA614501",
      "TN23SDA614502",
      "TN23SDA614503",
      "TN23SDA032153",
      "TN23SDA032164",
      "TN23SDA614507",
      "TN23SDA614508",
      "TN23SDA614509",
      "TN23SDA614511",
      "TN23SDA614512",
      "TN23SWA614516",
      "TN23SWA614523",
      "TN23SWA614524",
      "TN2024SDIA6930199",
      "TN2024SDIA6930200",
      "TN2024SDIA6930201",
      "TN2024SDIA6930202",
      "TN2024SDIA6930203",
      "TN2024SDIA6930204",
      "TN2024SDIA6930205",
      "TN2024SDIA6930206",
      "TN2024SDIA6930207",
      "TN2024SDIA6930208",
      "TN2024SDIA6930209",
      "TN2024SDIA6930210",
      "TN2024SDIA6930211",
      "TN2024SDIA6930212",
      "TN2024SWIA6930213",
      "TN2024SWIA6930214",
      "TN2024SWIA6930215",
      "TN2024SWIA6930216",
      "TN2024SWIA6930217",
      "TN2024SWIA6930218",
      "TN2024SWIA6930219",
      "TN2024SWIA6930220"
    ],
    "rank": [
      "CPL",
      "SGT",
      "SCUO",
      "CPL",
      "CPL",
      "CPL",
      "CQMS",
      "CSM",
      "CPL",
      "SGT",
      "SGT",
      "SGT",
      "CPL",
      "CUO",
      "CUO",
      "L/CPL",
      "L/CPL",
      "L/CPL",
      "L/CPL",
      "L/CPL",
      "L/CPL",
      "L/CPL",
      "L/CPL",
      "L/CPL",
      "L/CPL",
      "L/CPL",
      "L/CPL",
      "L/CPL",
      "CDT",
      "CDT",
      "CDT",
      "CDT",
      "CDT",
      "CDT",
      "CDT",
      "CDT",
      "CDT",
      "CDT",
      "CDT",
      "CDT",
      "CDT",
      "CDT",
      "CDT",
      "CDT",
      "CDT",
      "CDT",
      "CDT",
      "CDT",
      "CDT",
      "CDT"
    ],
    "year": [
      "III",
      "III",
      "III",
      "III",
      "III",
      "III",
      "III",
      "III",
      "III",
      "III",
      "III",
      "III",
      "III",
      "III",
      "III",
      "II",
      "II",
      "II",
      "II",
      "II",
      "II",
      "II",
      "II",
      "II",
      "II",
      "II",
      "II",
      "II",
      "I",
      "I",
      "I",
      "I",
      "I",
      "I",
      "I",
      "I",
      "I",
      "I",
      "I",
      "I",
      "I",
      "I",
      "I",
      "I",
      "I",
      "I",
      "I",
      "I",
      "I",
      "I"
    ],
    "department": [
      "ECE/C",
      "EEE",
      "MECH/A",
      "ECE/C",
      "IT/B",
      "MECH/B",
      "ECE/C",
      "AUTO",
      "MECH/B",
      "ECE/C",
      "CSE/B",
      "IT/A",
      "EEE",
      "ECE/A",
      "CSE/A",
      "CIVIL",
      "MECH",
      "AUTO",
      "MECH",
      "CSE/C",
      "ECE/A",
      "MECH",
      "MECH",
      "AI&DS/A",
      "MECH",
      "AI&DS/B",
      "EIE/A",
      "ECE/C",
      "MECH/A",
      "ECE/D",
      "CIVIL/A",
      "CIVIL/A",
      "ECE/C",
      "ECE/A",
      "EEE/A",
      "AIDS/B",
      "CSE/D",
      "ECE/A",
      "MECH/A",
      "MECH/A",
      "EEE/A",
      "MECH/A",
      "ECE/A",
      "IT/B",
      "ECE/B",
      "AIDS/B",
      "AIDS/B",
      "CSE/C",
      "ECE/A",
      "AIDS/A"
    ],
    "image_path": [
      "static/images/ncc/army/members1.webp",
      "static/images/ncc/army/members2.webp",
      "static/images/ncc/army/members3.webp",
      "static/images/ncc/army/members4.webp",
      "static/images/ncc/army/members5.webp",
      "static/images/ncc/army/members6.webp",
      "static/images/ncc/army/members7.webp",
      "static/images/ncc/army/members8.webp",
      "static/images/ncc/army/members9.webp",
      "static/images/ncc/army/members10.webp",
      "static/images/ncc/army/members11.webp",
      "static/images/ncc/army/members12.webp",
      "static/images/ncc/army/members13.webp",
      "static/images/ncc/army/members14.webp",
      "static/images/ncc/army/members15.webp",
      "static/images/ncc/army/members16.webp",
      "static/images/ncc/army/members17.webp",
      "static/images/ncc/army/members18.webp",
      "static/images/ncc/army/members19.webp",
      "static/images/ncc/army/members20.webp",
      "static/images/ncc/army/members21.webp",
      "static/images/ncc/army/members22.webp",
      "static/images/ncc/army/members23.webp",
      "static/images/ncc/army/members24.webp",
      "static/images/ncc/army/members25.webp",
      "static/images/ncc/army/members26.webp",
      "static/images/ncc/army/members27.webp",
      "static/images/ncc/army/members28.webp",
      "static/images/ncc/army/members29.webp",
      "static/images/ncc/army/members30.webp",
      "static/images/ncc/army/members31.webp",
      "static/images/ncc/army/members32.webp",
      "static/images/ncc/army/members33.webp",
      "static/images/ncc/army/members34.webp",
      "static/images/ncc/army/members35.webp",
      "static/images/ncc/army/members36.webp",
      "static/images/ncc/army/members37.webp",
      "static/images/ncc/army/members38.webp",
      "static/images/ncc/army/members39.webp",
      "static/images/ncc/army/members40.webp",
      "static/images/ncc/army/members41.webp",
      "static/images/ncc/army/members42.webp",
      "static/images/ncc/army/members43.webp",
      "static/images/ncc/army/members44.webp",
      "static/images/ncc/army/members45.webp",
      "static/images/ncc/army/members46.webp",
      "static/images/ncc/army/members47.webp",
      "static/images/ncc/army/members48.webp",
      "static/images/ncc/army/members49.webp",
      "static/images/ncc/army/members50.webp"
    ]
  },
  "events": {
    "image_path":[],
    "title": [],
    "des": []
  },
  "awards": {
    "title":[],
    "image_path": [],
      "des": []
  },
  "news": {"updates": []}
}]